sahi/__init__.py
sahi/annotation.py
sahi/auto_model.py
sahi/cli.py
sahi/constants.py
sahi/logger.py
sahi/predict.py
sahi/prediction.py
sahi/py.typed
sahi/slicing.py
sahi/models/__init__.py
sahi/models/base.py
sahi/models/detectron2.py
sahi/models/huggingface.py
sahi/models/mmdet.py
sahi/models/roboflow.py
sahi/models/rtdetr.py
sahi/models/torchvision.py
sahi/models/ultralytics.py
sahi/models/yolov5.py
sahi/postprocess/__init__.py
sahi/postprocess/combine.py
sahi/postprocess/utils.py
sahi/postprocess/legacy/__init__.py
sahi/postprocess/legacy/combine.py
sahi/scripts/__init__.py
sahi/scripts/coco2fiftyone.py
sahi/scripts/coco2yolo.py
sahi/scripts/coco_error_analysis.py
sahi/scripts/coco_evaluation.py
sahi/scripts/predict.py
sahi/scripts/predict_fiftyone.py
sahi/scripts/slice_coco.py
sahi/utils/__init__.py
sahi/utils/coco.py
sahi/utils/compatibility.py
sahi/utils/cv.py
sahi/utils/detectron2.py
sahi/utils/fiftyone.py
sahi/utils/file.py
sahi/utils/import_utils.py
sahi/utils/mmdet.py
sahi/utils/rtdetr.py
sahi/utils/shapely.py
sahi/utils/torch_utils.py
sahi/utils/torchvision.py
sahi/utils/yolov5.py
sahi-0.11.35.dist-info/METADATA
sahi-0.11.35.dist-info/WHEEL
sahi-0.11.35.dist-info/entry_points.txt
sahi-0.11.35.dist-info/licenses/LICENSE
sahi-0.11.35.dist-info/RECORD
