Metadata-Version: 2.4
Name: sahi
Version: 0.11.35
Summary: A vision library for performing sliced inference on large images/small objects
Project-URL: Homepage, https://github.com/obss/sahi
Project-URL: Source, https://github.com/obss/sahi
Project-URL: Documentation, https://github.com/obss/sahi/tree/main/docs
Project-URL: Bug Reports, https://github.com/obss/sahi/discussions/categories/q-a
Project-URL: Changelog, https://github.com/obss/sahi/releases
Maintainer: Fatih Cagatay Akyon (@fcakyon)
License-Expression: MIT
License-File: LICENSE
Classifier: Intended Audience :: Developers
Classifier: Intended Audience :: Science/Research
Classifier: License :: OSI Approved :: MIT License
Classifier: Operating System :: OS Independent
Classifier: Programming Language :: Python :: 3
Classifier: Programming Language :: Python :: 3.8
Classifier: Programming Language :: Python :: 3.9
Classifier: Programming Language :: Python :: 3.10
Classifier: Programming Language :: Python :: 3.11
Classifier: Programming Language :: Python :: 3.12
Classifier: Topic :: Software Development :: Libraries
Classifier: Topic :: Software Development :: Libraries :: Python Modules
Requires-Python: >=3.8
Requires-Dist: click
Requires-Dist: fire
Requires-Dist: opencv-python<=4.11.0.86
Requires-Dist: pillow>=8.2.0
Requires-Dist: pybboxes==0.1.6
Requires-Dist: pyyaml
Requires-Dist: requests
Requires-Dist: shapely>=2.0.0
Requires-Dist: terminaltables
Requires-Dist: tqdm>=4.48.2
Provides-Extra: all
Requires-Dist: inference>=0.51.5; (python_version >= '3.12') and extra == 'all'
Requires-Dist: onnx; (python_version >= '3.10') and extra == 'all'
Requires-Dist: onnxruntime; (python_version >= '3.10') and extra == 'all'
Requires-Dist: rfdetr>=1.1.0; (python_version >= '3.12') and extra == 'all'
Requires-Dist: torch; extra == 'all'
Requires-Dist: torchvision; extra == 'all'
Requires-Dist: transformers>=4.49.0; (python_version >= '3.9') and extra == 'all'
Requires-Dist: ultralytics>=8.0.0; extra == 'all'
Requires-Dist: yolov5<8.0.0,>=6.0.0; extra == 'all'
Provides-Extra: ci
Requires-Dist: fiftyone; extra == 'ci'
Requires-Dist: inference>=0.51.5; (python_version >= '3.12') and extra == 'ci'
Requires-Dist: onnx; (python_version >= '3.10') and extra == 'ci'
Requires-Dist: onnxruntime; (python_version >= '3.10') and extra == 'ci'
Requires-Dist: pycocotools>=2.0.7; extra == 'ci'
Requires-Dist: rfdetr>=1.1.0; (python_version >= '3.12') and extra == 'ci'
Requires-Dist: scikit-image; extra == 'ci'
Requires-Dist: torch==2.4.1+cpu; (python_version == '3.8' and platform_system != 'Darwin') and extra == 'ci'
Requires-Dist: torch==2.4.1; (python_version == '3.8' and platform_system == 'Darwin') and extra == 'ci'
Requires-Dist: torch==2.7.0+cpu; (python_version >= '3.9' and platform_system != 'Darwin') and extra == 'ci'
Requires-Dist: torch==2.7.0; (python_version >= '3.9' and platform_system == 'Darwin') and extra == 'ci'
Requires-Dist: torchvision==0.19.1+cpu; (python_version == '3.8' and platform_system != 'Darwin') and extra == 'ci'
Requires-Dist: torchvision==0.19.1; (python_version == '3.8' and platform_system == 'Darwin') and extra == 'ci'
Requires-Dist: torchvision==0.22.0+cpu; (python_version >= '3.9' and platform_system != 'Darwin') and extra == 'ci'
Requires-Dist: torchvision==0.22.0; (python_version >= '3.9' and platform_system == 'Darwin') and extra == 'ci'
Requires-Dist: transformers>=4.49.0; (python_version >= '3.9') and extra == 'ci'
Requires-Dist: ultralytics>=8.3.161; extra == 'ci'
Provides-Extra: mmdet
Requires-Dist: mmcv==2.1.0; (python_version == '3.11' and (platform_system != 'Darwin' or platform_machine != 'arm64')) and extra == 'mmdet'
Requires-Dist: mmdet==3.3.0; (python_version == '3.11' and (platform_system != 'Darwin' or platform_machine != 'arm64')) and extra == 'mmdet'
Requires-Dist: mmengine; (python_version == '3.11' and (platform_system != 'Darwin' or platform_machine != 'arm64')) and extra == 'mmdet'
Requires-Dist: numpy<2.0; (python_version == '3.11') and extra == 'mmdet'
Provides-Extra: onnx
Requires-Dist: onnx; (python_version >= '3.10') and extra == 'onnx'
Requires-Dist: onnxruntime; (python_version >= '3.10') and extra == 'onnx'
Provides-Extra: roboflow
Requires-Dist: inference>=0.51.5; (python_version >= '3.12') and extra == 'roboflow'
Requires-Dist: rfdetr>=1.1.0; (python_version >= '3.12') and extra == 'roboflow'
Provides-Extra: torch
Requires-Dist: torch; extra == 'torch'
Requires-Dist: torchvision; extra == 'torch'
Provides-Extra: transformers
Requires-Dist: transformers>=4.49.0; (python_version >= '3.9') and extra == 'transformers'
Provides-Extra: yolo
Requires-Dist: ultralytics>=8.0.0; extra == 'yolo'
Provides-Extra: yolov5
Requires-Dist: yolov5<8.0.0,>=6.0.0; extra == 'yolov5'
